pringles/__init__.py
pringles/backends/__init__.py
pringles/backends/web_display.py
pringles/backends/statics/basic.html
pringles/backends/statics/css/style.css
pringles/backends/statics/js/Canvas.js
pringles/backends/statics/js/ColorCodes.js
pringles/backends/statics/js/JSONModelGraphics.js
pringles/backends/statics/js/Link.js
pringles/backends/statics/js/Model.js
pringles/backends/statics/js/Port.js
pringles/backends/statics/js/Square.js
pringles/backends/statics/js/main.js
pringles/backends/statics/js/manifest.js
pringles/backends/statics/js/toposort.js
pringles/backends/statics/vendors/js/createjs/createjs-2013.12.12.min.js
pringles/backends/statics/vendors/js/jquery-3.2.1/jquery-3.2.1.min.js
pringles/models/__init__.py
pringles/models/errors.py
pringles/models/models.py
pringles/serializers/__init__.py
pringles/serializers/json.py
pringles/serializers/ma.py
pringles/simulator/__init__.py
pringles/simulator/errors.py
pringles/simulator/events.py
pringles/simulator/registry.py
pringles/simulator/simulation.py
pringles/simulator/simulator.py
pringles/simulator/registry_bootstrap/cpu.pringles
pringles/simulator/registry_bootstrap/generator.pringles
pringles/simulator/registry_bootstrap/qss1.pringles
pringles/simulator/registry_bootstrap/qss2.pringles
pringles/simulator/registry_bootstrap/qss3.pringles
pringles/simulator/registry_bootstrap/queue.pringles
pringles/simulator/registry_bootstrap/transducer.pringles
pringles/utils/__init__.py
pringles/utils/discovery.py
pringles/utils/errors.py
pringles/utils/plotting.py
pringles/utils/vtime.py
tests/__init__.py
tests/conftest.py
tests/test_atomic_metadata_extractor.py
tests/test_events.py
tests/test_model_ipython_display.py
tests/test_model_metadata_and_instanciation_integration.py
tests/test_model_translation.py
tests/test_simulation.py
tests/test_simulator.py
tests/test_utils.py
pringles_devs-2.0.1.dist-info/LICENSE
pringles_devs-2.0.1.dist-info/METADATA
pringles_devs-2.0.1.dist-info/WHEEL
pringles_devs-2.0.1.dist-info/top_level.txt
pringles_devs-2.0.1.dist-info/RECORD
