Metadata-Version: 2.1
Name: pringles-devs
Version: 2.0.1
Summary: A DEVS model composition library
Home-page: https://git-modsimu.exp.dc.uba.ar/colonelpringles/pringles
Author: Colonel Pringles
Classifier: Programming Language :: Python :: 3.9
Classifier: License :: OSI Approved :: GNU General Public License v3 (GPLv3)
Classifier: Operating System :: OS Independent
License-File: LICENSE
Requires-Dist: pandas ==2.2.1
Requires-Dist: ipython ==8.18.1
Requires-Dist: matplotlib ==3.8.3
Requires-Dist: asyncio ==3.4.3
Requires-Dist: tornado ==6.4.0
